trainingbar/__init__.py
trainingbar/_version.py
trainingbar/bar.py
trainingbar/cli.py
trainingbar/logger.py
trainingbar/utils.py
trainingbar/config/__init__.py
trainingbar/config/auth.json
trainingbar/config/prereqs.py
trainingbar/config/styles.py
trainingbar/handlers/__init__.py
trainingbar/handlers/gpu.py
trainingbar/handlers/host.py
trainingbar/handlers/network.py
trainingbar/handlers/tpu.py
trainingbar-0.0.2.dist-info/LICENSE
trainingbar-0.0.2.dist-info/METADATA
trainingbar-0.0.2.dist-info/WHEEL
trainingbar-0.0.2.dist-info/entry_points.txt
trainingbar-0.0.2.dist-info/top_level.txt
trainingbar-0.0.2.dist-info/RECORD
